specivar/__init__.py
specivar/specivar.py
specivar-0.0.12.dist-info/LICENSE
specivar-0.0.12.dist-info/METADATA
specivar-0.0.12.dist-info/WHEEL
specivar-0.0.12.dist-info/entry_points.txt
specivar-0.0.12.dist-info/top_level.txt
specivar-0.0.12.dist-info/RECORD
