Metadata-Version: 2.1
Name: specivar
Version: 0.0.12
Summary: Filter VCF to variants that are specific to a sample group
Home-page: https://gitlab.com/salk-tm/specivar
Author: Anthony Aylward
Author-email: aaylward@salk.edu
License: UNKNOWN
Platform: UNKNOWN
Classifier: Programming Language :: Python :: 3
Classifier: License :: OSI Approved :: MIT License
Classifier: Operating System :: OS Independent
License-File: LICENSE
Requires-Dist: pysam
